poetry_plugin_no_content_hash/__init__.py
poetry_plugin_no_content_hash/plugin.py
poetry_plugin_no_content_hash-1.0.0.dist-info/entry_points.txt
poetry_plugin_no_content_hash-1.0.0.dist-info/WHEEL
poetry_plugin_no_content_hash-1.0.0.dist-info/METADATA
poetry_plugin_no_content_hash-1.0.0.dist-info/RECORD
